omnipyrig/__init__.py
omnipyrig/omnipyrig.py
omnipyrig-1.0.1.dist-info/METADATA
omnipyrig-1.0.1.dist-info/WHEEL
omnipyrig-1.0.1.dist-info/top_level.txt
omnipyrig-1.0.1.dist-info/RECORD
