Metadata-Version: 2.1
Name: omnipyrig
Version: 1.0.1
Summary: A python wrapper for Omni-Rig
Author: 4Z1KD (Gil)
Author-email: <4z1kd@iarc.org>
Keywords: python,amateur radio,ham,omni-rig,omnirig,radio
Classifier: Development Status :: 4 - Beta
Classifier: Intended Audience :: Developers
Classifier: Programming Language :: Python :: 3
Classifier: Operating System :: Microsoft :: Windows
Requires-Dist: pywin32
